MANIFEST.in
README.txt
setup.py
django_lfstheme.egg-info/PKG-INFO
django_lfstheme.egg-info/SOURCES.txt
django_lfstheme.egg-info/dependency_links.txt
django_lfstheme.egg-info/not-zip-safe
django_lfstheme.egg-info/requires.txt
django_lfstheme.egg-info/top_level.txt
lfstheme/__init__.py
lfstheme/locale/cs/LC_MESSAGES/django.mo
lfstheme/locale/cs/LC_MESSAGES/django.po
lfstheme/locale/de/LC_MESSAGES/django.mo
lfstheme/locale/de/LC_MESSAGES/django.po
lfstheme/locale/en/LC_MESSAGES/django.po
lfstheme/locale/es/LC_MESSAGES/django.mo
lfstheme/locale/es/LC_MESSAGES/django.po
lfstheme/locale/es_MX/LC_MESSAGES/django.mo
lfstheme/locale/es_MX/LC_MESSAGES/django.po
lfstheme/locale/fr/LC_MESSAGES/django.mo
lfstheme/locale/fr/LC_MESSAGES/django.po
lfstheme/locale/it/LC_MESSAGES/django.mo
lfstheme/locale/it/LC_MESSAGES/django.po
lfstheme/locale/nl/LC_MESSAGES/django.mo
lfstheme/locale/nl/LC_MESSAGES/django.po
lfstheme/locale/pl/LC_MESSAGES/django.mo
lfstheme/locale/pl/LC_MESSAGES/django.po
lfstheme/locale/ro/LC_MESSAGES/django.mo
lfstheme/locale/ro/LC_MESSAGES/django.po
lfstheme/locale/ru/LC_MESSAGES/django.mo
lfstheme/locale/ru/LC_MESSAGES/django.po
lfstheme/locale/zh_CN/LC_MESSAGES/django.mo
lfstheme/locale/zh_CN/LC_MESSAGES/django.po
lfstheme/locale/zh_TW/LC_MESSAGES/django.mo
lfstheme/locale/zh_TW/LC_MESSAGES/django.po
lfstheme/static/blueprint/ie.css
lfstheme/static/blueprint/print.css
lfstheme/static/blueprint/screen.css
lfstheme/static/blueprint/plugins/buttons/readme.txt
lfstheme/static/blueprint/plugins/buttons/screen.css
lfstheme/static/blueprint/plugins/buttons/icons/cross.png
lfstheme/static/blueprint/plugins/buttons/icons/key.png
lfstheme/static/blueprint/plugins/buttons/icons/tick.png
lfstheme/static/blueprint/plugins/fancy-type/readme.txt
lfstheme/static/blueprint/plugins/fancy-type/screen.css
lfstheme/static/blueprint/plugins/link-icons/readme.txt
lfstheme/static/blueprint/plugins/link-icons/screen.css
lfstheme/static/blueprint/plugins/link-icons/icons/doc.png
lfstheme/static/blueprint/plugins/link-icons/icons/email.png
lfstheme/static/blueprint/plugins/link-icons/icons/external.png
lfstheme/static/blueprint/plugins/link-icons/icons/feed.png
